hello_art256/__init__.py
hello_art256/hello.py
hello_art256-0.0.1.dist-info/METADATA
hello_art256-0.0.1.dist-info/WHEEL
hello_art256-0.0.1.dist-info/licenses/LICENSE
hello_art256-0.0.1.dist-info/RECORD
